[{"firstName":"FirstName1","lastName":"LastName1","position":"Position1","departament":"Position1","salary":1001,"FirstName":"FirstName1","LastName":"LastName1","Position":"Position1","Departament":"Position1","Salary":1001,"HourRate":5.005},{"firstName":"FirstName2","lastName":"LastName2","position":"Position2","departament":"Position2","salary":1002,"FirstName":"FirstName2","LastName":"LastName2","Position":"Position2","Departament":"Position2","Salary":1002,"HourRate":5.01},{"firstName":"FirstName3","lastName":"LastName3","position":"Position3","departament":"Position3","salary":1003,"FirstName":"FirstName3","LastName":"LastName3","Position":"Position3","Departament":"Position3","Salary":1003,"HourRate":5.015},{"firstName":"FirstName4","lastName":"LastName4","position":"Position4","departament":"Position4","salary":1004,"FirstName":"FirstName4","LastName":"LastName4","Position":"Position4","Departament":"Position4","Salary":1004,"HourRate":5.02},{"firstName":"FirstName5","lastName":"LastName5","position":"Position5","departament":"Position5","salary":1005,"FirstName":"FirstName5","LastName":"LastName5","Position":"Position5","Departament":"Position5","Salary":1005,"HourRate":5.025}]